Metadata-Version: 2.1
Name: quickauth
Version: 0.2.21
Summary: QuickAuth: A Quick User-Password Authentication for Python
Home-page: https://github.com/valency/quickauth/
Author: Ye Ding
Author-email: guiewy@gmail.com
License: UNKNOWN
Keywords: auth,authentication
Platform: UNKNOWN
